{
  "1": [
    {
      "code": "MA101",
      "display": "Mathematics-I",
      "papers": {
        "2017": {
          "display": "2017",
          "mid": "",
          "end": ""
        },
        "2018": {
          "display": "2018",
          "mid": "",
          "end": ""
        },
        "2019": {
          "display": "2019",
          "mid": "",
          "end": ""
        },
        "2020": {
          "display": "2020",
          "mid": "",
          "end": ""
        },
        "2021": {
          "display": "2021",
          "mid": "",
          "end": ""
        },
        "2022": {
          "display": "2022",
          "mid": "",
          "end": ""
        },
        "2023": {
          "display": "2023",
          "mid": "",
          "end": ""
        },
        "2024": {
          "display": "2024",
          "mid": "",
          "end": ""
        }
      }
    },
    {
      "code": "MA102",
      "display": "Mathematics-II",
      "papers": {
        "2017": {
          "display": "2017",
          "mid": "",
          "end": ""
        },
        "2018": {
          "display": "2018",
          "mid": "",
          "end": ""
        },
        "2019": {
          "display": "2019",
          "mid": "",
          "end": ""
        },
        "2020": {
          "display": "2020",
          "mid": "",
          "end": ""
        },
        "2021": {
          "display": "2021",
          "mid": "",
          "end": ""
        },
        "2022": {
          "display": "2022",
          "mid": "",
          "end": ""
        },
        "2023": {
          "display": "2023",
          "mid": "",
          "end": ""
        },
        "2024": {
          "display": "2024",
          "mid": "",
          "end": ""
        }
      }
    }
  ]
}
